LICENSE
README.rst
erlang.py
setup.py
erlang_py.egg-info/PKG-INFO
erlang_py.egg-info/SOURCES.txt
erlang_py.egg-info/dependency_links.txt
erlang_py.egg-info/top_level.txt