Metadata-Version: 2.1
Name: erlang-py
Version: 2.0.4
Summary: Erlang Binary Term Format for Python
Home-page: https://github.com/okeuday/erlang_py
Author: Michael Truog
Author-email: mjtruog@protonmail.com
License: MIT
Platform: UNKNOWN
Classifier: Development Status :: 5 - Production/Stable
Classifier: Intended Audience :: Developers
Classifier: License :: OSI Approved :: MIT License
Classifier: Operating System :: OS Independent
Classifier: Programming Language :: Python
Classifier: Programming Language :: Python :: 3
Classifier: Programming Language :: Erlang
Classifier: Topic :: Software Development :: Libraries :: Python Modules
Classifier: Topic :: System :: Distributed Computing
